incognito_anonymizer/__init__.py
incognito_anonymizer/__main__.py
incognito_anonymizer/analyzer.py
incognito_anonymizer/anonymizer.py
incognito_anonymizer/anotate.py
incognito_anonymizer/cli.py
incognito_anonymizer/mask.py
incognito_anonymizer-1.2.0.dist-info/METADATA
incognito_anonymizer-1.2.0.dist-info/WHEEL
incognito_anonymizer-1.2.0.dist-info/licenses/LICENSE
incognito_anonymizer-1.2.0.dist-info/RECORD
