Metadata-Version: 2.4
Name: incognito-anonymizer
Version: 1.2.0
Summary: A module to anonymize french text data
Project-URL: Repository, https://github.com/Micropot/incognito
Author-email: Arthur Lamard <arthur@lamard.org>
License-File: LICENSE
Keywords: anonymizer,incognito
Requires-Python: >=3.10
Requires-Dist: dkpro-cassis>=0.10.1
Requires-Dist: flash>=1.0.3
Requires-Dist: flashtext>=2.7
Requires-Dist: pydantic>=2.10.6
Requires-Dist: regex>=2024.11.6
